fast_grpc/__init__.py
fast_grpc/app.py
fast_grpc/context.py
fast_grpc/middleware.py
fast_grpc/proto.py
fast_grpc/py.typed
fast_grpc/service.py
fast_grpc/types.py
fast_grpc/utils.py
python_fast_grpc-0.3.4.dist-info/LICENSE
python_fast_grpc-0.3.4.dist-info/METADATA
python_fast_grpc-0.3.4.dist-info/WHEEL
python_fast_grpc-0.3.4.dist-info/RECORD
