Metadata-Version: 2.1
Name: python-fast-grpc
Version: 0.3.4
Summary: Fast to Code gRPC in Python
Home-page: https://github.com/taogeYT/fast-grpc
Author: taogeYT
Author-email: li_yatao@outlook.com
Requires-Python: >=3.9
Classifier: Programming Language :: Python :: 3
Classifier: Programming Language :: Python :: 3.9
Classifier: Programming Language :: Python :: 3.10
Classifier: Programming Language :: Python :: 3.11
Classifier: Programming Language :: Python :: 3.12
Classifier: Programming Language :: Python :: 3.13
Requires-Dist: grpcio (>=1.43.0)
Requires-Dist: grpcio-reflection (>=1.43.0)
Requires-Dist: grpcio-tools (>=1.43.0)
Requires-Dist: jinja2 (>=2.11.2)
Requires-Dist: logzero (>=1.7.0,<2.0.0)
Requires-Dist: protobuf (>=4.21.1)
Requires-Dist: pydantic (>=2.0,<3.0.0)
Project-URL: Repository, https://github.com/taogeYT/fast-grpc
